pure_nrng_package/__init__.py
pure_nrng_package/pure_nrng_module.py
rng_util_package/__init__.py
rng_util_package/rng_util_module.py
pure_nrng-1.1.0.dist-info/LICENSE
pure_nrng-1.1.0.dist-info/METADATA
pure_nrng-1.1.0.dist-info/WHEEL
pure_nrng-1.1.0.dist-info/top_level.txt
pure_nrng-1.1.0.dist-info/RECORD
