Metadata-Version: 2.1
Name: pure-nrng
Version: 1.1.0
Summary: Generate multi-precision non-deterministic random Numbers.
Home-page: https://github.com/fsssosei/Pure_NRNG
Author: sosei
Author-email: fss.sosei@gmail.com
License: GNU Affero General Public License v3
Keywords: NRNG,TRNG,Random,Multiple-precision
Platform: UNKNOWN
Classifier: Development Status :: 5 - Production/Stable
Classifier: License :: OSI Approved :: GNU Affero General Public License v3
Classifier: Programming Language :: Python :: 3.8
Requires-Python: >=3.8
Requires-Dist: gmpy2 (>=2.0.8)
